maga_pm/__init__.py
maga_pm/cdn_traffic.py
maga_pm/cli.py
maga_pm/i18n.py
maga_pm/package_manager.py
maga_pm/policy_simulator.py
maga_pm/real_pip_manager.py
maga_pm/traffic_tax.py
maga_pm/usa_colors.py
maga_pm-11.4.6.dist-info/METADATA
maga_pm-11.4.6.dist-info/WHEEL
maga_pm-11.4.6.dist-info/entry_points.txt
maga_pm-11.4.6.dist-info/top_level.txt
maga_pm-11.4.6.dist-info/RECORD
