Metadata-Version: 2.4
Name: maga-pm
Version: 11.4.6
Summary: MAGA Package Manager - Advanced package management with policy-based controls
Home-page: https://gitee.com/ruin321/maga-pm
Author: ruin321
Author-email: 3791944372@qq.com
Keywords: maga,package manager,policy,control,management
Classifier: Development Status :: 4 - Beta
Classifier: Intended Audience :: Developers
Classifier: Topic :: Software Development :: Build Tools
Classifier: License :: OSI Approved :: MIT License
Classifier: Programming Language :: Python :: 3
Classifier: Programming Language :: Python :: 3.6
Classifier: Programming Language :: Python :: 3.7
Classifier: Programming Language :: Python :: 3.8
Classifier: Programming Language :: Python :: 3.9
Classifier: Programming Language :: Python :: 3.10
Classifier: Programming Language :: Python :: 3.11
Classifier: Programming Language :: Python :: 3.12
Classifier: Operating System :: OS Independent
Classifier: Environment :: Console
Classifier: Topic :: Utilities
Requires-Python: >=3.6
Requires-Dist: requests>=2.25.0
Requires-Dist: colorama>=0.4.0
Requires-Dist: tqdm>=4.65.0
Requires-Dist: nodejs>=0.1.1
Dynamic: author
Dynamic: author-email
Dynamic: classifier
Dynamic: description
Dynamic: description-content-type
Dynamic: home-page
Dynamic: keywords
Dynamic: requires-dist
Dynamic: requires-python
Dynamic: summary
